{"overview": {"Engaged": "67%", "Distracted": "33%", "Drowsy": "5%"}, "avg_attention": 67, "max_attention": 99, "min_attention": 35, "blocks": [{"id": 0, "attention": 56, "restlessness": 49}, {"id": 1, "attention": 38, "restlessness": 70}, {"id": 2, "attention": 63, "restlessness": 37}, {"id": 3, "attention": 85, "restlessness": 17}, {"id": 4, "attention": 46, "restlessness": 53}, {"id": 5, "attention": 91, "restlessness": 1}, {"id": 6, "attention": 41, "restlessness": 59}, {"id": 7, "attention": 89, "restlessness": 14}, {"id": 8, "attention": 97, "restlessness": 0}, {"id": 9, "attention": 52, "restlessness": 42}, {"id": 10, "attention": 97, "restlessness": 0}, {"id": 11, "attention": 97, "restlessness": 0}, {"id": 12, "attention": 35, "restlessness": 57}, {"id": 13, "attention": 48, "restlessness": 50}, {"id": 14, "attention": 93, "restlessness": 0}, {"id": 15, "attention": 95, "restlessness": 1}, {"id": 16, "attention": 49, "restlessness": 44}, {"id": 17, "attention": 74, "restlessness": 32}, {"id": 18, "attention": 79, "restlessness": 20}, {"id": 19, "attention": 46, "restlessness": 52}, {"id": 20, "attention": 65, "restlessness": 32}, {"id": 21, "attention": 99, "restlessness": 3}, {"id": 22, "attention": 57, "restlessness": 33}, {"id": 23, "attention": 60, "restlessness": 40}, {"id": 24, "attention": 41, "restlessness": 64}], "attention_time": [88, 64, 88, 68, 86, 83, 75, 72], "suggestions": ["Re-engage lowest attention students now.", "Vary teaching method; try quick activity.", "Ask a direct question to reset focus."]}